arcgis_sdk/__init__.py
arcgis_sdk-0.0.12.dist-info/DESCRIPTION.rst
arcgis_sdk-0.0.12.dist-info/METADATA
arcgis_sdk-0.0.12.dist-info/RECORD
arcgis_sdk-0.0.12.dist-info/WHEEL
arcgis_sdk-0.0.12.dist-info/metadata.json
arcgis_sdk-0.0.12.dist-info/top_level.txt
